lab_orchestrator_lib/__init__.py
lab_orchestrator_lib/custom_exceptions.py
lab_orchestrator_lib/template_engine.py
lab_orchestrator_lib/controller/__init__.py
lab_orchestrator_lib/controller/adapter_controller.py
lab_orchestrator_lib/controller/controller.py
lab_orchestrator_lib/controller/controller_collection.py
lab_orchestrator_lib/controller/kubernetes_controller.py
lab_orchestrator_lib/database/__init__.py
lab_orchestrator_lib/database/adapter.py
lab_orchestrator_lib/kubernetes/__init__.py
lab_orchestrator_lib/kubernetes/api.py
lab_orchestrator_lib/kubernetes/config.py
lab_orchestrator_lib/model/__init__.py
lab_orchestrator_lib/model/model.py
lab_orchestrator_lib/templates/__init__.py
lab_orchestrator_lib/templates/namespace_template.yaml
lab_orchestrator_lib/templates/network_policy_template.yaml
lab_orchestrator_lib/templates/vmi_template.yaml
lab_orchestrator_lib-1.0.1.dist-info/LICENSE
lab_orchestrator_lib-1.0.1.dist-info/METADATA
lab_orchestrator_lib-1.0.1.dist-info/WHEEL
lab_orchestrator_lib-1.0.1.dist-info/top_level.txt
lab_orchestrator_lib-1.0.1.dist-info/zip-safe
lab_orchestrator_lib-1.0.1.dist-info/RECORD
